copier_templates_extensions-0.3.2.dist-info/METADATA
copier_templates_extensions-0.3.2.dist-info/WHEEL
copier_templates_extensions-0.3.2.dist-info/entry_points.txt
copier_templates_extensions-0.3.2.dist-info/licenses/LICENSE
copier_templates_extensions/__init__.py
copier_templates_extensions/py.typed
copier_templates_extensions-0.3.2.dist-info/RECORD
